[
  {
    "id": "doc_1781414541340_aju6gu",
    "title": "Lythuyet_toan10",
    "description": "abcd",
    "file": "TOMTAT-TOAN10-KNTT.pdf",
    "type": "pdf",
    "grade": "10",
    "subject": "Toán"
  },
  {
    "id": "doc_1781414585426_xx0408",
    "title": "Lythuyet11",
    "description": "abca",
    "file": "TOMTAT-TOAN11-KNTT.pdf",
    "type": "pdf",
    "grade": "11",
    "subject": "Toán"
  },
  {
    "id": "doc_1781414647295_9a17jb",
    "title": "lythyet12",
    "description": "abx",
    "file": "TOMTAT-TOAN12-KNTT.pdf",
    "type": "pdf",
    "grade": "12",
    "subject": "Toán"
  }
]