[
  {
    "id": "de_hs_24J67O_11A4_1780132365904_532",
    "title": "de_hs_24J67O",
    "week": "1",
    "class": "11A4",
    "open": "2026-05-30",
    "close": "2026-06-30",
    "html": "de_hs_24J67O.html"
  },
  {
    "id": "de_hs_24J67O_11A5_1780132365904_770",
    "title": "de_hs_24J67O",
    "week": "1",
    "class": "11A5",
    "open": "2026-05-30",
    "close": "2026-06-30",
    "html": "de_hs_24J67O.html"
  },
  {
    "id": "de_hs_EXFQTDD_11A4_1780132365904_22",
    "title": "de_hs_EXFQTDD",
    "week": "1",
    "class": "11A4",
    "open": "2026-05-30",
    "close": "2026-06-30",
    "html": "de_hs_EXFQTDD.html"
  },
  {
    "id": "de_hs_EXFQTDD_11A5_1780132365904_127",
    "title": "de_hs_EXFQTDD",
    "week": "1",
    "class": "11A5",
    "open": "2026-05-30",
    "close": "2026-06-30",
    "html": "de_hs_EXFQTDD.html"
  },
  {
    "id": "de_hs_EXYB5CR_11A4_1780132365904_677",
    "title": "de_hs_EXYB5CR",
    "week": "1",
    "class": "11A4",
    "open": "2026-05-30",
    "close": "2026-06-30",
    "html": "de_hs_EXYB5CR.html"
  },
  {
    "id": "de_hs_EXYB5CR_11A5_1780132365904_831",
    "title": "de_hs_EXYB5CR",
    "week": "1",
    "class": "11A5",
    "open": "2026-05-30",
    "close": "2026-06-30",
    "html": "de_hs_EXYB5CR.html"
  },
  {
    "id": "de_hs_UQE7QA_11A4_1780132365904_545",
    "title": "de_hs_UQE7QA",
    "week": "1",
    "class": "11A4",
    "open": "2026-05-30",
    "close": "2026-06-30",
    "html": "de_hs_UQE7QA.html"
  },
  {
    "id": "de_hs_UQE7QA_11A5_1780132365904_759",
    "title": "de_hs_UQE7QA",
    "week": "1",
    "class": "11A5",
    "open": "2026-05-30",
    "close": "2026-06-30",
    "html": "de_hs_UQE7QA.html"
  },
  {
    "id": "de_hs_VRNZ4P_11A4_1780132365904_955",
    "title": "de_hs_VRNZ4P",
    "week": "1",
    "class": "11A4",
    "open": "2026-05-30",
    "close": "2026-06-30",
    "html": "de_hs_VRNZ4P.html"
  },
  {
    "id": "de_hs_VRNZ4P_11A5_1780132365904_46",
    "title": "de_hs_VRNZ4P",
    "week": "1",
    "class": "11A5",
    "open": "2026-05-30",
    "close": "2026-06-30",
    "html": "de_hs_VRNZ4P.html"
  },
  {
    "id": "de_hs_XOKWP2_11A4_1780132365904_105",
    "title": "de_hs_XOKWP2",
    "week": "1",
    "class": "11A4",
    "open": "2026-05-30",
    "close": "2026-06-30",
    "html": "de_hs_XOKWP2.html"
  },
  {
    "id": "de_hs_XOKWP2_11A5_1780132365904_280",
    "title": "de_hs_XOKWP2",
    "week": "1",
    "class": "11A5",
    "open": "2026-05-30",
    "close": "2026-06-30",
    "html": "de_hs_XOKWP2.html"
  }
]